terraform_exporter_plugin/__init__.py
terraform_exporter_plugin/generated/plugin_pb2.py
terraform_exporter_plugin/generated/plugin_pb2.pyi
terraform_exporter_plugin/generated/plugin_pb2_grpc.py
terraform_exporter_plugin/lib/net.py
terraform_exporter_plugin/lib/serve.py
terraform_exporter_plugin/lib/types.py
terraform_exporter_plugin-0.1.0.dist-info/LICENSE
terraform_exporter_plugin-0.1.0.dist-info/METADATA
terraform_exporter_plugin-0.1.0.dist-info/WHEEL
terraform_exporter_plugin-0.1.0.dist-info/RECORD
